tangram_weather/WindFieldLayer.vue
tangram_weather/__init__.py
tangram_weather/arpege.py
tangram_weather/index.ts
tangram_weather/dist-frontend/__vite-optional-peer-dep_geotiff_weatherlayers-gl_false-Cjw5BclT.js
tangram_weather/dist-frontend/__vite-optional-peer-dep_geotiff_weatherlayers-gl_false-Cjw5BclT.js.map
tangram_weather/dist-frontend/index.css
tangram_weather/dist-frontend/index.js
tangram_weather/dist-frontend/index.js.map
tangram_weather/dist-frontend/plugin.json
tangram_weather/package.json
tangram_weather-0.2.1.dist-info/METADATA
tangram_weather-0.2.1.dist-info/WHEEL
tangram_weather-0.2.1.dist-info/entry_points.txt
tangram_weather-0.2.1.dist-info/RECORD
