Metadata-Version: 2.4
Name: tangram_weather
Version: 0.2.1
Summary: Weather data integration plugin for tangram
Author-email: Xavier Olive <git@xoolive.org>
License-Expression: AGPL-3.0
Classifier: Development Status :: 4 - Beta
Classifier: Intended Audience :: Science/Research
Classifier: License :: OSI Approved :: GNU Affero General Public License v3
Classifier: Programming Language :: Python :: 3
Classifier: Programming Language :: Python :: 3.10
Classifier: Programming Language :: Python :: 3.11
Classifier: Programming Language :: Python :: 3.12
Classifier: Programming Language :: Python :: 3.13
Classifier: Topic :: Scientific/Engineering :: Atmospheric Science
Classifier: Topic :: Scientific/Engineering :: Visualization
Requires-Python: >=3.10
Requires-Dist: cfgrib>=0.9.15.0
Requires-Dist: numpy>=2
Requires-Dist: orjson>=3.10.18
Requires-Dist: pandas
Requires-Dist: pillow>=10
Requires-Dist: tangram-core>=0.2.0
Requires-Dist: tqdm>=4.67.1
Requires-Dist: xarray>=2025.6.1
